Workbook

Sheet README
A1: Loan Portfolio Revenue Forecast & Scenario Model
A3: Forecasts 12-month net interest income for a small-business/professional loan portfolio, segmented by credit tier, with a scenario toggle (Base / Best / Stress) and a rate x delinquency sensitivity grid.
A5: How to use this workbook
A6: 1. Portfolio Summary — starting balance, rate, and delinquency rate by credit tier (sourced from loan_portfolio.csv).
A7: 2. Assumptions — scenario levers (yellow cells). Change the 'Selected Scenario' dropdown to switch Base / Best / Stress.
A8: 3. Revenue Forecast — 12-month projection driven by the selected scenario; updates automatically.
A9: 4. Sensitivity Analysis — a rate-shift x delinquency-stress grid showing Year-1 net interest income under each combination.
A10: 5. Dashboard — chart and KPI summary of the forecast.
A12: Legend
A13: Blue text | B13: hardcoded input, sourced from data or stated assumption
A14: Black text | B14: formula
A15: Yellow fill | B15: scenario lever — change these to test alternate assumptions
A17: Note: portfolio inputs are derived from a synthetically generated dataset (see the companion GitHub repo, loan-portfolio-risk) for demonstration purposes, not real lending data.

Sheet Portfolio Summary
A1: Portfolio Summary — Starting Position
A2: Source: loan_portfolio.csv (synthetic dataset, 8,000 loans) — see loan-portfolio-risk repo
A4: Credit Tier | B4: Loan Count | C4: Outstanding Balance ($) | D4: Weighted Avg Rate | E4: Delinquency Rate
A5: Prime | B5: 3250 | C5: 1.4252215e+08 | D5: 0.0613 | E5: 0.0978
A6: Near-Prime | B6: 3018 | C6: 85402697 | D6: 0.1061 | E6: 0.1968
A7: Subprime | B7: 1732 | C7: 28221867 | D7: 0.1599 | E7: 0.3718
A8: Total / Blended | B8: =SUM(B5:B7) -> 8000 | C8: =SUM(C5:C7) -> 2.5614671e+08 | D8: =SUMPRODUCT(D5:D7,C5:C7)/C8 -> 0.087100515 | E8: =SUMPRODUCT(E5:E7,C5:C7)/C8 -> 0.16099682

Sheet Assumptions
A1: Scenario Assumptions
A3: Selected Scenario: | B3: Base
A6: Scenario | B6: Monthly Volume Growth | C6: Rate Shift (bps) | D6: Delinquency Stress Multiplier
A7: Base | B7: 0.01 | C7: 0 | D7: 1
A8: Best | B8: 0.02 | C8: -50 | D8: 0.8
A9: Stress | B9: -0.01 | C9: 150 | D9: 1.4
A11: Active scenario values (pulled via INDEX/MATCH from the selected scenario above):
A13: Monthly Volume Growth | B13: =INDEX(B7:B9,MATCH($B$3,A7:A9,0)) -> 0.01
A14: Rate Shift (bps) | B14: =INDEX(C7:C9,MATCH($B$3,A7:A9,0)) -> 0
A15: Delinquency Stress Multiplier | B15: =INDEX(D7:D9,MATCH($B$3,A7:A9,0)) -> 1
A17: Assumptions are illustrative for demonstration. Base case volume growth and rate-shift levers are stated assumptions, not fitted to historical performance.

Sheet Revenue Forecast
A1: 12-Month Net Interest Income Forecast
A2: ="Scenario: "&Assumptions!$B$3 -> Scenario: Base
A4: Credit Tier | B4: Start | C4: Month 1 | D4: Month 2 | E4: Month 3 | F4: Month 4 | G4: Month 5 | H4: Month 6 | I4: Month 7 | J4: Month 8 | K4: Month 9 | L4: Month 10 | M4: Month 11 | N4: Month 12
A5: Prime | B5: ='Portfolio Summary'!C5 -> 1.4252215e+08 | C5: =B5*(1+Assumptions!$B$13) -> 1.4394737e+08 | D5: =C5*(1+Assumptions!$B$13) -> 1.4538684e+08 | E5: =D5*(1+Assumptions!$B$13) -> 1.4684071e+08 | F5: =E5*(1+Assumptions!$B$13) -> 1.4830912e+08 | G5: =F5*(1+Assumptions!$B$13) -> 1.4979221e+08 | H5: =G5*(1+Assumptions!$B$13) -> 1.5129013e+08 | I5: =H5*(1+Assumptions!$B$13) -> 1.5280303e+08 | J5: =I5*(1+Assumptions!$B$13) -> 1.5433106e+08 | ... N5: =M5*(1+Assumptions!$B$13) -> 1.6059752e+08
A6: Near-Prime | B6: ='Portfolio Summary'!C6 -> 85402697 | C6: =B6*(1+Assumptions!$B$13) -> 86256724 | D6: =C6*(1+Assumptions!$B$13) -> 87119291 | E6: =D6*(1+Assumptions!$B$13) -> 87990484 | F6: =E6*(1+Assumptions!$B$13) -> 88870389 | G6: =F6*(1+Assumptions!$B$13) -> 89759093 | H6: =G6*(1+Assumptions!$B$13) -> 90656684 | I6: =H6*(1+Assumptions!$B$13) -> 91563251 | J6: =I6*(1+Assumptions!$B$13) -> 92478883 | ... N6: =M6*(1+Assumptions!$B$13) -> 96233897
A7: Subprime | B7: ='Portfolio Summary'!C7 -> 28221867 | C7: =B7*(1+Assumptions!$B$13) -> 28504085 | D7: =C7*(1+Assumptions!$B$13) -> 28789126 | E7: =D7*(1+Assumptions!$B$13) -> 29077018 | F7: =E7*(1+Assumptions!$B$13) -> 29367788 | G7: =F7*(1+Assumptions!$B$13) -> 29661466 | H7: =G7*(1+Assumptions!$B$13) -> 29958080 | I7: =H7*(1+Assumptions!$B$13) -> 30257661 | J7: =I7*(1+Assumptions!$B$13) -> 30560238 | ... N7: =M7*(1+Assumptions!$B$13) -> 31801106
A8: Total Balance | B8: =SUM(B5:B7) -> 2.5614671e+08 | C8: =SUM(C5:C7) -> 2.5870818e+08 | D8: =SUM(D5:D7) -> 2.6129526e+08 | E8: =SUM(E5:E7) -> 2.6390821e+08 | F8: =SUM(F5:F7) -> 2.6654729e+08 | G8: =SUM(G5:G7) -> 2.6921277e+08 | H8: =SUM(H5:H7) -> 2.7190489e+08 | I8: =SUM(I5:I7) -> 2.7462394e+08 | ... N8: =SUM(N5:N7) -> 2.8863252e+08
A10: Net Interest Income (Monthly) | C10: =C5*$B$13/12*(1-$B$18)+C6*$B$14/12*(1-$B$19)+C7*$B$15/12*(1-$B$20) -> 1514579.8 | D10: =D5*$B$13/12*(1-$B$18)+D6*$B$14/12*(1-$B$19)+D7*$B$15/12*(1-$B$20) -> 1529725.6 | E10: =E5*$B$13/12*(1-$B$18)+E6*$B$14/12*(1-$B$19)+E7*$B$15/12*(1-$B$20) -> 1545022.9 | F10: =F5*$B$13/12*(1-$B$18)+F6*$B$14/12*(1-$B$19)+F7*$B$15/12*(1-$B$20) -> 1560473.1 | G10: =G5*$B$13/12*(1-$B$18)+G6*$B$14/12*(1-$B$19)+G7*$B$15/12*(1-$B$20) -> 1576077.8 | H10: =H5*$B$13/12*(1-$B$18)+H6*$B$14/12*(1-$B$19)+H7*$B$15/12*(1-$B$20) -> 1591838.6 | I10: =I5*$B$13/12*(1-$B$18)+I6*$B$14/12*(1-$B$19)+I7*$B$15/12*(1-$B$20) -> 1607757 | J10: =J5*$B$13/12*(1-$B$18)+J6*$B$14/12*(1-$B$19)+J7*$B$15/12*(1-$B$20) -> 1623834.5 | ... N10: =N5*$B$13/12*(1-$B$18)+N6*$B$14/12*(1-$B$19)+N7*$B$15/12*(1-$B$20) -> 1689768.7
A12: Effective Annual Rate by Tier (rate + scenario shift)
A13: Prime | B13: ='Portfolio Summary'!D5+Assumptions!$B$14/10000 -> 0.0613
A14: Near-Prime | B14: ='Portfolio Summary'!D6+Assumptions!$B$14/10000 -> 0.1061
A15: Subprime | B15: ='Portfolio Summary'!D7+Assumptions!$B$14/10000 -> 0.1599
A17: Stressed Delinquency Rate by Tier
A18: Prime | B18: ='Portfolio Summary'!E5*Assumptions!$B$15 -> 0.0978
A19: Near-Prime | B19: ='Portfolio Summary'!E6*Assumptions!$B$15 -> 0.1968
A20: Subprime | B20: ='Portfolio Summary'!E7*Assumptions!$B$15 -> 0.3718
A21: Cumulative Net Interest Income | C21: =C10 -> 1514579.8 | D21: =C21+D10 -> 3044305.4 | E21: =D21+E10 -> 4589328.3 | F21: =E21+F10 -> 6149801.3 | G21: =F21+G10 -> 7725879.1 | H21: =G21+H10 -> 9317717.7 | I21: =H21+I10 -> 10925475 | J21: =I21+J10 -> 12549309 | K21: =J21+K10 -> 14189382 | ... N21: =M21+N10 -> 19208663

Sheet Sensitivity Analysis
A1: Year-1 Net Interest Income Sensitivity
A2: Rows: delinquency stress multiplier · Columns: rate shift (bps) · Values: Year-1 total NII
A4: Delinq. Stress \ Rate Shift | B4: -100 bps | C4: -50 bps | D4: 0 bps | E4: +100 bps | F4: +200 bps
A5: 0.80x | B5: ='Portfolio Summary'!C5*('Portfolio Summary'!D5+-100/10000)*(1-'Portfolio Summary'!E5*0.8)+'Portfolio Summary'!C6*('Portfolio Summary'!D6+-100/10000)*(1-'Portfolio Summary'!E6*0.8)+'Portfolio Summary'!C7*('Portfolio Summary'!D7+-100/10000)*(1-'Portfolio Summary'!E7*0.8) -> 16626551 | C5: ='Portfolio Summary'!C5*('Portfolio Summary'!D5+-50/10000)*(1-'Portfolio Summary'!E5*0.8)+'Portfolio Summary'!C6*('Portfolio Summary'!D6+-50/10000)*(1-'Portfolio Summary'!E6*0.8)+'Portfolio Summary'!C7*('Portfolio Summary'!D7+-50/10000)*(1-'Portfolio Summary'!E7*0.8) -> 17742330 | D5: ='Portfolio Summary'!C5*('Portfolio Summary'!D5+0/10000)*(1-'Portfolio Summary'!E5*0.8)+'Portfolio Summary'!C6*('Portfolio Summary'!D6+0/10000)*(1-'Portfolio Summary'!E6*0.8)+'Portfolio Summary'!C7*('Portfolio Summary'!D7+0/10000)*(1-'Portfolio Summary'!E7*0.8) -> 18858108 | E5: ='Portfolio Summary'!C5*('Portfolio Summary'!D5+100/10000)*(1-'Portfolio Summary'!E5*0.8)+'Portfolio Summary'!C6*('Portfolio Summary'!D6+100/10000)*(1-'Portfolio Summary'!E6*0.8)+'Portfolio Summary'!C7*('Portfolio Summary'!D7+100/10000)*(1-'Portfolio Summary'!E7*0.8) -> 21089665 | F5: ='Portfolio Summary'!C5*('Portfolio Summary'!D5+200/10000)*(1-'Portfolio Summary'!E5*0.8)+'Portfolio Summary'!C6*('Portfolio Summary'!D6+200/10000)*(1-'Portfolio Summary'!E6*0.8)+'Portfolio Summary'!C7*('Portfolio Summary'!D7+200/10000)*(1-'Portfolio Summary'!E7*0.8) -> 23321221
A6: 1.00x | B6: ='Portfolio Summary'!C5*('Portfolio Summary'!D5+-100/10000)*(1-'Portfolio Summary'!E5*1)+'Portfolio Summary'!C6*('Portfolio Summary'!D6+-100/10000)*(1-'Portfolio Summary'!E6*1)+'Portfolio Summary'!C7*('Portfolio Summary'!D7+-100/10000)*(1-'Portfolio Summary'!E7*1) -> 15845928 | C6: ='Portfolio Summary'!C5*('Portfolio Summary'!D5+-50/10000)*(1-'Portfolio Summary'!E5*1)+'Portfolio Summary'!C6*('Portfolio Summary'!D6+-50/10000)*(1-'Portfolio Summary'!E6*1)+'Portfolio Summary'!C7*('Portfolio Summary'!D7+-50/10000)*(1-'Portfolio Summary'!E7*1) -> 16920468 | D6: ='Portfolio Summary'!C5*('Portfolio Summary'!D5+0/10000)*(1-'Portfolio Summary'!E5*1)+'Portfolio Summary'!C6*('Portfolio Summary'!D6+0/10000)*(1-'Portfolio Summary'!E6*1)+'Portfolio Summary'!C7*('Portfolio Summary'!D7+0/10000)*(1-'Portfolio Summary'!E7*1) -> 17995008 | E6: ='Portfolio Summary'!C5*('Portfolio Summary'!D5+100/10000)*(1-'Portfolio Summary'!E5*1)+'Portfolio Summary'!C6*('Portfolio Summary'!D6+100/10000)*(1-'Portfolio Summary'!E6*1)+'Portfolio Summary'!C7*('Portfolio Summary'!D7+100/10000)*(1-'Portfolio Summary'!E7*1) -> 20144087 | F6: ='Portfolio Summary'!C5*('Portfolio Summary'!D5+200/10000)*(1-'Portfolio Summary'!E5*1)+'Portfolio Summary'!C6*('Portfolio Summary'!D6+200/10000)*(1-'Portfolio Summary'!E6*1)+'Portfolio Summary'!C7*('Portfolio Summary'!D7+200/10000)*(1-'Portfolio Summary'!E7*1) -> 22293166
A7: 1.20x | B7: ='Portfolio Summary'!C5*('Portfolio Summary'!D5+-100/10000)*(1-'Portfolio Summary'!E5*1.2)+'Portfolio Summary'!C6*('Portfolio Summary'!D6+-100/10000)*(1-'Portfolio Summary'!E6*1.2)+'Portfolio Summary'!C7*('Portfolio Summary'!D7+-100/10000)*(1-'Portfolio Summary'!E7*1.2) -> 15065306 | C7: ='Portfolio Summary'!C5*('Portfolio Summary'!D5+-50/10000)*(1-'Portfolio Summary'!E5*1.2)+'Portfolio Summary'!C6*('Portfolio Summary'!D6+-50/10000)*(1-'Portfolio Summary'!E6*1.2)+'Portfolio Summary'!C7*('Portfolio Summary'!D7+-50/10000)*(1-'Portfolio Summary'!E7*1.2) -> 16098606 | D7: ='Portfolio Summary'!C5*('Portfolio Summary'!D5+0/10000)*(1-'Portfolio Summary'!E5*1.2)+'Portfolio Summary'!C6*('Portfolio Summary'!D6+0/10000)*(1-'Portfolio Summary'!E6*1.2)+'Portfolio Summary'!C7*('Portfolio Summary'!D7+0/10000)*(1-'Portfolio Summary'!E7*1.2) -> 17131907 | E7: ='Portfolio Summary'!C5*('Portfolio Summary'!D5+100/10000)*(1-'Portfolio Summary'!E5*1.2)+'Portfolio Summary'!C6*('Portfolio Summary'!D6+100/10000)*(1-'Portfolio Summary'!E6*1.2)+'Portfolio Summary'!C7*('Portfolio Summary'!D7+100/10000)*(1-'Portfolio Summary'!E7*1.2) -> 19198508 | F7: ='Portfolio Summary'!C5*('Portfolio Summary'!D5+200/10000)*(1-'Portfolio Summary'!E5*1.2)+'Portfolio Summary'!C6*('Portfolio Summary'!D6+200/10000)*(1-'Portfolio Summary'!E6*1.2)+'Portfolio Summary'!C7*('Portfolio Summary'!D7+200/10000)*(1-'Portfolio Summary'!E7*1.2) -> 21265110
A8: 1.40x | B8: ='Portfolio Summary'!C5*('Portfolio Summary'!D5+-100/10000)*(1-'Portfolio Summary'!E5*1.4)+'Portfolio Summary'!C6*('Portfolio Summary'!D6+-100/10000)*(1-'Portfolio Summary'!E6*1.4)+'Portfolio Summary'!C7*('Portfolio Summary'!D7+-100/10000)*(1-'Portfolio Summary'!E7*1.4) -> 14284683 | C8: ='Portfolio Summary'!C5*('Portfolio Summary'!D5+-50/10000)*(1-'Portfolio Summary'!E5*1.4)+'Portfolio Summary'!C6*('Portfolio Summary'!D6+-50/10000)*(1-'Portfolio Summary'!E6*1.4)+'Portfolio Summary'!C7*('Portfolio Summary'!D7+-50/10000)*(1-'Portfolio Summary'!E7*1.4) -> 15276745 | D8: ='Portfolio Summary'!C5*('Portfolio Summary'!D5+0/10000)*(1-'Portfolio Summary'!E5*1.4)+'Portfolio Summary'!C6*('Portfolio Summary'!D6+0/10000)*(1-'Portfolio Summary'!E6*1.4)+'Portfolio Summary'!C7*('Portfolio Summary'!D7+0/10000)*(1-'Portfolio Summary'!E7*1.4) -> 16268806 | E8: ='Portfolio Summary'!C5*('Portfolio Summary'!D5+100/10000)*(1-'Portfolio Summary'!E5*1.4)+'Portfolio Summary'!C6*('Portfolio Summary'!D6+100/10000)*(1-'Portfolio Summary'!E6*1.4)+'Portfolio Summary'!C7*('Portfolio Summary'!D7+100/10000)*(1-'Portfolio Summary'!E7*1.4) -> 18252930 | F8: ='Portfolio Summary'!C5*('Portfolio Summary'!D5+200/10000)*(1-'Portfolio Summary'!E5*1.4)+'Portfolio Summary'!C6*('Portfolio Summary'!D6+200/10000)*(1-'Portfolio Summary'!E6*1.4)+'Portfolio Summary'!C7*('Portfolio Summary'!D7+200/10000)*(1-'Portfolio Summary'!E7*1.4) -> 20237054
A9: 1.60x | B9: ='Portfolio Summary'!C5*('Portfolio Summary'!D5+-100/10000)*(1-'Portfolio Summary'!E5*1.6)+'Portfolio Summary'!C6*('Portfolio Summary'!D6+-100/10000)*(1-'Portfolio Summary'!E6*1.6)+'Portfolio Summary'!C7*('Portfolio Summary'!D7+-100/10000)*(1-'Portfolio Summary'!E7*1.6) -> 13504060 | C9: ='Portfolio Summary'!C5*('Portfolio Summary'!D5+-50/10000)*(1-'Portfolio Summary'!E5*1.6)+'Portfolio Summary'!C6*('Portfolio Summary'!D6+-50/10000)*(1-'Portfolio Summary'!E6*1.6)+'Portfolio Summary'!C7*('Portfolio Summary'!D7+-50/10000)*(1-'Portfolio Summary'!E7*1.6) -> 14454883 | D9: ='Portfolio Summary'!C5*('Portfolio Summary'!D5+0/10000)*(1-'Portfolio Summary'!E5*1.6)+'Portfolio Summary'!C6*('Portfolio Summary'!D6+0/10000)*(1-'Portfolio Summary'!E6*1.6)+'Portfolio Summary'!C7*('Portfolio Summary'!D7+0/10000)*(1-'Portfolio Summary'!E7*1.6) -> 15405706 | E9: ='Portfolio Summary'!C5*('Portfolio Summary'!D5+100/10000)*(1-'Portfolio Summary'!E5*1.6)+'Portfolio Summary'!C6*('Portfolio Summary'!D6+100/10000)*(1-'Portfolio Summary'!E6*1.6)+'Portfolio Summary'!C7*('Portfolio Summary'!D7+100/10000)*(1-'Portfolio Summary'!E7*1.6) -> 17307352 | F9: ='Portfolio Summary'!C5*('Portfolio Summary'!D5+200/10000)*(1-'Portfolio Summary'!E5*1.6)+'Portfolio Summary'!C6*('Portfolio Summary'!D6+200/10000)*(1-'Portfolio Summary'!E6*1.6)+'Portfolio Summary'!C7*('Portfolio Summary'!D7+200/10000)*(1-'Portfolio Summary'!E7*1.6) -> 19208998
A11: Read as: rate shift and delinquency stress are independent levers (not a single combined 'good/bad' axis). At this portfolio's rate and delinquency levels, a +200 bps rate increase raises NII by more than 1.60x delinquency stress erodes it — so the bottom-right cell can exceed the 0 bps / 1.00x base case (row 6, middle column). That's a real finding: this book's revenue is more rate-sensitive than delinquency-sensitive in the ranges tested, which is useful context for how a rate-rising vs. credit-deteriorating environment would actually affect the portfolio differently.

Sheet Dashboard
A1: Portfolio Forecast Dashboard
A2: ="Scenario: "&Assumptions!$B$3 -> Scenario: Base
A4: Starting Total Balance | B4: ='Revenue Forecast'!B8 -> 2.5614671e+08
A5: Month-12 Total Balance | B5: ='Revenue Forecast'!N8 -> 2.8863252e+08
A6: Year-1 Net Interest Income | B6: ='Revenue Forecast'!N21 -> 19208663
A7: Blended Starting Rate | B7: ='Portfolio Summary'!D8 -> 0.087100515
A8: Blended Starting Delinquency Rate | B8: ='Portfolio Summary'!E8 -> 0.16099682
